spines/__init__.py
spines/_version.py
spines/decorators.py
spines/exceptions.py
spines/model.py
spines/config/__init__.py
spines/config/base.py
spines/config/config.py
spines/config/core.py
spines/config/utils.py
spines/core/__init__.py
spines/core/base.py
spines/core/decorators.py
spines/core/utils.py
spines/parameters/__init__.py
spines/parameters/base.py
spines/parameters/core.py
spines/parameters/decorators.py
spines/parameters/factories.py
spines/parameters/mixins.py
spines/parameters/store.py
spines/project/__init__.py
spines/project/utils.py
spines/transforms/__init__.py
spines/transforms/base.py
spines/transforms/core.py
spines/utils/__init__.py
spines/utils/file.py
spines/vendor/__init__.py
spines/vendor/autopep8.py
spines/vendor/pycodestyle.py
spines/versioning/__init__.py
spines/versioning/base.py
spines/versioning/core.py
spines/versioning/utils.py
spines-0.0.6.dist-info/AUTHORS
spines-0.0.6.dist-info/LICENSE
spines-0.0.6.dist-info/METADATA
spines-0.0.6.dist-info/WHEEL
spines-0.0.6.dist-info/top_level.txt
spines-0.0.6.dist-info/RECORD
