Metadata-Version: 2.1
Name: spines
Version: 0.0.6
Summary: Backbones for parameterized models.
Home-page: https://www.github.com/douglasdaly/spines
Author: Douglas Daly
Author-email: contact@douglasdaly.com
License: MIT
Project-URL: Source Code, https://www.github.com/douglasdaly/spines
Project-URL: Documentation, https://spines.readthedocs.io/
Keywords: spines parameterized models
Platform: UNKNOWN
Classifier: Development Status :: 2 - Pre-Alpha
Classifier: Programming Language :: Python :: 3.6
Classifier: Programming Language :: Python :: 3.7
Classifier: Intended Audience :: Science/Research
Classifier: Topic :: Scientific/Engineering
Classifier: License :: OSI Approved :: MIT License
Requires-Dist: parver
Requires-Dist: toml
Requires-Dist: xxhash
